{"name":"TenMinuteblog","body":"tenMinuteBlog\r\n=============\r\n\r\n10분만에 만드는 블로그\r\nMeteor써서 빠른 프로토타이핑에 도전하자.\r\n\r\n### Features\r\n1. 블로그 목록을 만든다.\r\n1. 새 포스트를 생성한다.\r\n1. 시간 순으로 정렬한다.\r\n1. 포스트를 삭제한다.\r\n1. 포스트를 수정한다.\r\n\r\n### 학습과제\r\n1. Backbone의 client쪽 routing을 이해한다.\r\n1. coffeescript로 이벤트와 컬렉션을 매핑하는 방법을 익힌다.\r\n1. minimongo 로 데이터를 접근하고 뷰에 반영하는 과정을 연습해본다.\r\n1. 완성한 프로젝트를 deploy해보고 bundle로 묶어본다.\r\n\r\n### References\r\n* [Meteor](http://meteor.com/)\r\n* [Backbone](http://documentcloud.github.com/backbone/)\r\n* [MongoDB](http://www.mongodb.org/)\r\n* [Socket.IO](http://socket.io/)\r\n* [Bootstrap](http://twitter.github.com/bootstrap)\r\n\r\n### Install\r\n1. node.js + npm (http://nodejs.org/#download)\r\n1. meteor (http://meteor.com/)\r\n1. Coffeescript (npm install -g coffee-script)\r\n1. jQuery plug-in (meteor add jquery)\r\n1. less plug-in (meteor add less)\r\n1. coffeescript plug-in (meteor add coffeescript)\r\n1. bootstrap plug-in (meteor add bootstrap)\r\n","tagline":"10분만에 만드는 블로그","google":"","note":"Don't delete this file! It's used internally to help with page regeneration."}